script/__init__.py
script/scunet-ng.py
script/scunet.py
scunet-1.1.0.data/scripts/scunet
scunet-1.1.0.data/scripts/scunet.bat
scunet-1.1.0.data/scripts/scunet.py
scunet-1.1.0.dist-info/License
scunet-1.1.0.dist-info/METADATA
scunet-1.1.0.dist-info/WHEEL
scunet-1.1.0.dist-info/top_level.txt
scunet-1.1.0.dist-info/RECORD
