Metadata-Version: 2.1
Name: scunet
Version: 1.1.0
Summary: login scunet in terminal
Home-page: https://github.com/iansmith123/SCUNET
Author: Les1ie
Author-email: me@les1ie.com
License: GPL v3
Platform: UNKNOWN
Requires-Dist: requests
